noisemix/__init__.py
noisemix/data.py
noisemix/formats.py
noisemix/noise.py
noisemix/perturbation.py
noisemix/utils.py
noisemix-0.1.1.dist-info/METADATA
noisemix-0.1.1.dist-info/RECORD
noisemix-0.1.1.dist-info/WHEEL
noisemix-0.1.1.dist-info/top_level.txt
