Metadata-Version: 2.1
Name: noisemix
Version: 0.1.1
Summary: NoiseMix is a library for data generation for text datasets.
Home-page: https://github.com/noisemix/noisemix
Author: Anooshik Vartnian
Author-email: anooshik_vartanian@edu.aua.com
License: MIT
Platform: UNKNOWN
